swh/lister/__init__.py
swh/lister/cli.py
swh/lister/pattern.py
swh/lister/py.typed
swh/lister/utils.py
swh/lister/arch/__init__.py
swh/lister/arch/lister.py
swh/lister/arch/tasks.py
swh/lister/arch/tests/__init__.py
swh/lister/arch/tests/test_lister.py
swh/lister/arch/tests/test_tasks.py
swh/lister/arch/tests/data/fake_archlinux_archives_init.sh
swh/lister/arch/tests/data/https_archive.archlinux.org/packages_d_dialog
swh/lister/arch/tests/data/https_archive.archlinux.org/packages_g_gnome-code-assistance
swh/lister/arch/tests/data/https_archive.archlinux.org/packages_g_gzip
swh/lister/arch/tests/data/https_archive.archlinux.org/packages_l_libasyncns
swh/lister/arch/tests/data/https_archive.archlinux.org/packages_m_mercurial
swh/lister/arch/tests/data/https_archive.archlinux.org/packages_p_python-hglib
swh/lister/arch/tests/data/https_archive.archlinux.org/repos_last_community_os_x86_64_community.files.tar.gz
swh/lister/arch/tests/data/https_archive.archlinux.org/repos_last_core_os_x86_64_core.files.tar.gz
swh/lister/arch/tests/data/https_archive.archlinux.org/repos_last_extra_os_x86_64_extra.files.tar.gz
swh/lister/arch/tests/data/https_uk.mirror.archlinuxarm.org/aarch64_community_community.files.tar.gz
swh/lister/arch/tests/data/https_uk.mirror.archlinuxarm.org/aarch64_core_core.files.tar.gz
swh/lister/arch/tests/data/https_uk.mirror.archlinuxarm.org/aarch64_extra_extra.files.tar.gz
swh/lister/arch/tests/data/https_uk.mirror.archlinuxarm.org/armv7h_community_community.files.tar.gz
swh/lister/arch/tests/data/https_uk.mirror.archlinuxarm.org/armv7h_core_core.files.tar.gz
swh/lister/arch/tests/data/https_uk.mirror.archlinuxarm.org/armv7h_extra_extra.files.tar.gz
swh/lister/aur/__init__.py
swh/lister/aur/lister.py
swh/lister/aur/tasks.py
swh/lister/aur/tests/__init__.py
swh/lister/aur/tests/test_lister.py
swh/lister/aur/tests/test_tasks.py
swh/lister/aur/tests/data/fake_aur_packages.sh
swh/lister/aur/tests/data/packages-meta-v1.json.gz
swh_lister-7.1.0.dist-info/licenses/AUTHORS
swh_lister-7.1.0.dist-info/licenses/LICENSE
swh_lister-7.1.0.dist-info/METADATA
swh_lister-7.1.0.dist-info/WHEEL
swh_lister-7.1.0.dist-info/entry_points.txt
swh_lister-7.1.0.dist-info/top_level.txt
swh_lister-7.1.0.dist-info/RECORD
