Metadata-Version: 2.4
Name: swh.lister
Version: 7.1.0
Summary: Software Heritage lister
Author-email: Software Heritage developers <swh-devel@inria.fr>
Project-URL: Homepage, https://gitlab.softwareheritage.org/swh/devel/swh-lister
Project-URL: Bug Reports, https://gitlab.softwareheritage.org/swh/devel/swh-lister/-/issues
Project-URL: Funding, https://www.softwareheritage.org/donate
Project-URL: Documentation, https://docs.softwareheritage.org/devel/swh-lister/
Project-URL: Source, https://gitlab.softwareheritage.org/swh/devel/swh-lister.git
Classifier: Programming Language :: Python :: 3
Classifier: Intended Audience :: Developers
Classifier: License :: OSI Approved :: GNU General Public License v3 (GPLv3)
Classifier: Operating System :: OS Independent
Classifier: Development Status :: 5 - Production/Stable
Requires-Python: >=3.9
License-File: LICENSE
License-File: AUTHORS
Requires-Dist: beautifulsoup4>=4.13.3
Requires-Dist: breezy>=3.3.12
Requires-Dist: dateparser
Requires-Dist: dulwich
Requires-Dist: iso8601
Requires-Dist: launchpadlib
Requires-Dist: looseversion
Requires-Dist: lxml
Requires-Dist: mercurial
Requires-Dist: ndjson
Requires-Dist: psycopg
Requires-Dist: pyreadr
Requires-Dist: python_debian
Requires-Dist: python-magic
Requires-Dist: repomd
Requires-Dist: requests
Requires-Dist: setuptools
Requires-Dist: subvertpy
Requires-Dist: tenacity>=8.4.2
Requires-Dist: testing.postgresql
Requires-Dist: toml
Requires-Dist: swh.core[db]>=4.0.0
Requires-Dist: swh.scheduler>=3.0.0
Provides-Extra: testing
Requires-Dist: celery-types; extra == "testing"
Requires-Dist: pandas; extra == "testing"
Requires-Dist: pandas-stubs; extra == "testing"
Requires-Dist: pytest>=8.1; extra == "testing"
Requires-Dist: pytest-mock; extra == "testing"
Requires-Dist: requests_mock; extra == "testing"
Requires-Dist: swh.scheduler[pytest]>=3.1.0; extra == "testing"
Requires-Dist: types-beautifulsoup4; extra == "testing"
Requires-Dist: types-dateparser; extra == "testing"
Requires-Dist: types-pyyaml; extra == "testing"
Requires-Dist: types-requests; extra == "testing"
Requires-Dist: types-toml; extra == "testing"
Requires-Dist: types-lxml; extra == "testing"
Dynamic: license-file
